OPDM/OPDM_SOAP_API.py
OPDM/__init__.py
OPDM/_version.py
opdm_api-0.1.3.dist-info/LICENSE
opdm_api-0.1.3.dist-info/METADATA
opdm_api-0.1.3.dist-info/WHEEL
opdm_api-0.1.3.dist-info/top_level.txt
opdm_api-0.1.3.dist-info/RECORD
